{
    "title": "Connect your Crypto Wallet and get TestNet MTCs!",
    "description": "We recommend using MetaMask.",
    "buttons": {
        "connect": {
            "text": "Connect Wallet"
        }, 
        "disconnect": {
            "text": "Disconnect"
        },
        "claim": {
            "text": "Send me TestNet MTC",
            "stages": {
                "claim": {
                    "text": "Send me TestNet MTC"
                },
                "loading": {
                    "text": "Requesting TestNet MTCs..."
                },
                "claimed": {
                    "text": "Remaining time: "
                }
            }
        }
    },
    "modal": {
        "verify": {
            "text": "Verify"
        }
    }
}